example_package_lars_k/__init__.py
example_package_lars_k/example.py
example_package_lars_k-0.0.1.dist-info/METADATA
example_package_lars_k-0.0.1.dist-info/WHEEL
example_package_lars_k-0.0.1.dist-info/licenses/LICENSE
example_package_lars_k-0.0.1.dist-info/RECORD
