Metadata-Version: 2.1
Name: example_package_lars_k
Version: 0.0.1
Summary: Testing how to create a package for python.
Project-URL: Homepage, https://github.com/LarsKluijtmans/test-package
Project-URL: Issues, https://github.com/LarsKluijtmans/test-package/issues
Author-email: Example Author <info@lk-software.com>
License-File: LICENSE
Classifier: License :: OSI Approved :: MIT License
Classifier: Operating System :: OS Independent
Classifier: Programming Language :: Python :: 3
Requires-Python: >=3.10
